odoo/addons/ssi_general_audit_worksheet_audit_working_plan/README.rst
odoo/addons/ssi_general_audit_worksheet_audit_working_plan/__init__.py
odoo/addons/ssi_general_audit_worksheet_audit_working_plan/__manifest__.py
odoo/addons/ssi_general_audit_worksheet_audit_working_plan/data/general_audit_worksheet_type_data.xml
odoo/addons/ssi_general_audit_worksheet_audit_working_plan/data/approval_template/general_audit_ws_cbbbaf4.xml
odoo/addons/ssi_general_audit_worksheet_audit_working_plan/data/ir_sequence/general_audit_ws_cbbbaf4.xml
odoo/addons/ssi_general_audit_worksheet_audit_working_plan/data/policy_template/general_audit_ws_cbbbaf4.xml
odoo/addons/ssi_general_audit_worksheet_audit_working_plan/data/sequence_template/general_audit_ws_cbbbaf4.xml
odoo/addons/ssi_general_audit_worksheet_audit_working_plan/models/__init__.py
odoo/addons/ssi_general_audit_worksheet_audit_working_plan/models/general_audit_competency_ugprade.py
odoo/addons/ssi_general_audit_worksheet_audit_working_plan/models/general_audit_ws_cbbbaf4.py
odoo/addons/ssi_general_audit_worksheet_audit_working_plan/models/general_audit_ws_cbbbaf4_team_allocation.py
odoo/addons/ssi_general_audit_worksheet_audit_working_plan/models/general_audit_ws_cbbbaf4_team_competency.py
odoo/addons/ssi_general_audit_worksheet_audit_working_plan/security/ir.model.access.csv
odoo/addons/ssi_general_audit_worksheet_audit_working_plan/security/ir_module_category_data.xml
odoo/addons/ssi_general_audit_worksheet_audit_working_plan/security/res_group_data.xml
odoo/addons/ssi_general_audit_worksheet_audit_working_plan/security/ir_model_access/general_audit_ws_cbbbaf4.xml
odoo/addons/ssi_general_audit_worksheet_audit_working_plan/security/ir_rule/general_audit_ws_cbbbaf4.xml
odoo/addons/ssi_general_audit_worksheet_audit_working_plan/security/res_group/general_audit_ws_cbbbaf4.xml
odoo/addons/ssi_general_audit_worksheet_audit_working_plan/static/description/icon.png
odoo14_addon_ssi_general_audit_worksheet_audit_working_plan-14.0.1.2.0.dist-info/METADATA
odoo14_addon_ssi_general_audit_worksheet_audit_working_plan-14.0.1.2.0.dist-info/WHEEL
odoo14_addon_ssi_general_audit_worksheet_audit_working_plan-14.0.1.2.0.dist-info/top_level.txt
odoo14_addon_ssi_general_audit_worksheet_audit_working_plan-14.0.1.2.0.dist-info/RECORD
